{
  "name": "Untitled",
  "DesktopAudioDevice1": {
    "prev_ver": 536936448,
    "name": "Desktop Audio",
    "uuid": "25dce8c4-81bc-4f1e-901d-656c8850b4c4",
    "id": "pulse_output_capture",
    "versioned_id": "pulse_output_capture",
    "settings": {
      "device_id": "default"
    },
    "mixers": 255,
    "sync": 0,
    "flags": 0,
    "volume": 1.0,
    "balance": 0.5,
    "enabled": true,
    "muted": false,
    "push-to-mute": false,
    "push-to-mute-delay": 0,
    "push-to-talk": false,
    "push-to-talk-delay": 0,
    "hotkeys": {
      "libobs.mute": [],
      "libobs.unmute": [],
      "libobs.push-to-mute": [],
      "libobs.push-to-talk": []
    },
    "deinterlace_mode": 0,
    "deinterlace_field_order": 0,
    "monitoring_type": 0,
    "private_settings": {}
  },
  "AuxAudioDevice1": {
    "prev_ver": 536936448,
    "name": "Mic/Aux",
    "uuid": "528d1851-b791-4e1f-bb22-6ceeece265a7",
    "id": "pulse_input_capture",
    "versioned_id": "pulse_input_capture",
    "settings": {
      "device_id": "default"
    },
    "mixers": 255,
    "sync": 0,
    "flags": 0,
    "volume": 1.0,
    "balance": 0.5,
    "enabled": true,
    "muted": false,
    "push-to-mute": false,
    "push-to-mute-delay": 0,
    "push-to-talk": false,
    "push-to-talk-delay": 0,
    "hotkeys": {
      "libobs.mute": [],
      "libobs.unmute": [],
      "libobs.push-to-mute": [],
      "libobs.push-to-talk": []
    },
    "deinterlace_mode": 0,
    "deinterlace_field_order": 0,
    "monitoring_type": 0,
    "private_settings": {}
  },
  "sources": [
    {
      "prev_ver": 536936448,
      "name": "Display Capture (XSHM)",
      "uuid": "88c92ea2-534e-4bf9-a8b1-a171bc01cb16",
      "id": "xshm_input_v2",
      "versioned_id": "xshm_input_v2",
      "settings": {
        "screen": 0
      },
      "mixers": 0,
      "sync": 0,
      "flags": 0,
      "volume": 1.0,
      "balance": 0.5,
      "enabled": true,
      "muted": false,
      "push-to-mute": false,
      "push-to-mute-delay": 0,
      "push-to-talk": false,
      "push-to-talk-delay": 0,
      "hotkeys": {},
      "deinterlace_mode": 0,
      "deinterlace_field_order": 0,
      "monitoring_type": 0,
      "private_settings": {}
    },
    {
      "prev_ver": 536936448,
      "name": "DroidCam OBS",
      "uuid": "af4e7c74-c743-4944-a370-54927e540610",
      "id": "droidcam_obs",
      "versioned_id": "droidcam_obs",
      "settings": {
        "device_list": "IB9SRWSK6T8T65AA",
        "enable_aduio": true,
        "cur_dev_id": "IB9SRWSK6T8T65AA",
        "cur_dev_ip": "127.0.0.1",
        "cur_dev_type": 2,
        "activated": true,
        "remote_url": "http://127.0.0.1:4747"
      },
      "mixers": 255,
      "sync": 0,
      "flags": 0,
      "volume": 1.0,
      "balance": 0.5,
      "enabled": true,
      "muted": false,
      "push-to-mute": false,
      "push-to-mute-delay": 0,
      "push-to-talk": false,
      "push-to-talk-delay": 0,
      "hotkeys": {
        "libobs.mute": [],
        "libobs.unmute": [],
        "libobs.push-to-mute": [],
        "libobs.push-to-talk": []
      },
      "deinterlace_mode": 0,
      "deinterlace_field_order": 0,
      "monitoring_type": 0,
      "private_settings": {},
      "filters": [
        {
          "prev_ver": 536936448,
          "name": "Noise Suppression",
          "uuid": "fecf339a-af5c-41fe-8ea2-7aa63eb9537f",
          "id": "noise_suppress_filter",
          "versioned_id": "noise_suppress_filter_v2",
          "settings": {},
          "mixers": 255,
          "sync": 0,
          "flags": 0,
          "volume": 1.0,
          "balance": 0.5,
          "enabled": true,
          "muted": false,
          "push-to-mute": false,
          "push-to-mute-delay": 0,
          "push-to-talk": false,
          "push-to-talk-delay": 0,
          "hotkeys": {},
          "deinterlace_mode": 0,
          "deinterlace_field_order": 0,
          "monitoring_type": 0,
          "private_settings": {}
        }
      ]
    },
    {
      "prev_ver": 536936448,
      "name": "Scene",
      "uuid": "76acccec-a99a-4c0f-b249-2e2eefd5f0cb",
      "id": "scene",
      "versioned_id": "scene",
      "settings": {
        "id_counter": 2,
        "custom_size": false,
        "items": [
          {
            "name": "Display Capture (XSHM)",
            "source_uuid": "88c92ea2-534e-4bf9-a8b1-a171bc01cb16",
            "visible": true,
            "locked": true,
            "rot": 0.0,
            "scale_ref": {
              "x": 1366.0,
              "y": 768.0
            },
            "align": 5,
            "bounds_type": 0,
            "bounds_align": 0,
            "bounds_crop": false,
            "crop_left": 0,
            "crop_top": 0,
            "crop_right": 0,
            "crop_bottom": 0,
            "id": 1,
            "group_item_backup": false,
            "pos": {
              "x": 0.0,
              "y": 0.0
            },
            "pos_rel": {
              "x": -1.7786458730697632,
              "y": -1.0
            },
            "scale": {
              "x": 1.0,
              "y": 1.0
            },
            "scale_rel": {
              "x": 1.0,
              "y": 1.0
            },
            "bounds": {
              "x": 0.0,
              "y": 0.0
            },
            "bounds_rel": {
              "x": 0.0,
              "y": 0.0
            },
            "scale_filter": "disable",
            "blend_method": "default",
            "blend_type": "normal",
            "show_transition": {
              "duration": 300
            },
            "hide_transition": {
              "duration": 300
            },
            "private_settings": {}
          },
          {
            "name": "DroidCam OBS",
            "source_uuid": "af4e7c74-c743-4944-a370-54927e540610",
            "visible": true,
            "locked": true,
            "rot": 0.0,
            "scale_ref": {
              "x": 1366.0,
              "y": 768.0
            },
            "align": 5,
            "bounds_type": 0,
            "bounds_align": 0,
            "bounds_crop": false,
            "crop_left": 0,
            "crop_top": 0,
            "crop_right": 0,
            "crop_bottom": 0,
            "id": 2,
            "group_item_backup": false,
            "pos": {
              "x": 1192.0,
              "y": 637.0
            },
            "pos_rel": {
              "x": 1.3255208730697632,
              "y": 0.6588541269302368
            },
            "scale": {
              "x": 0.2718749940395355,
              "y": 0.27291667461395264
            },
            "scale_rel": {
              "x": 0.2718749940395355,
              "y": 0.27291667461395264
            },
            "bounds": {
              "x": 0.0,
              "y": 0.0
            },
            "bounds_rel": {
              "x": 0.0,
              "y": 0.0
            },
            "scale_filter": "disable",
            "blend_method": "default",
            "blend_type": "normal",
            "show_transition": {
              "duration": 300
            },
            "hide_transition": {
              "duration": 300
            },
            "private_settings": {}
          }
        ]
      },
      "mixers": 0,
      "sync": 0,
      "flags": 0,
      "volume": 1.0,
      "balance": 0.5,
      "enabled": true,
      "muted": false,
      "push-to-mute": false,
      "push-to-mute-delay": 0,
      "push-to-talk": false,
      "push-to-talk-delay": 0,
      "hotkeys": {
        "OBSBasic.SelectScene": [],
        "libobs.show_scene_item.1": [],
        "libobs.hide_scene_item.1": [],
        "libobs.show_scene_item.2": [],
        "libobs.hide_scene_item.2": []
      },
      "deinterlace_mode": 0,
      "deinterlace_field_order": 0,
      "monitoring_type": 0,
      "canvas_uuid": "6c69626f-6273-4c00-9d88-c5136d61696e",
      "private_settings": {}
    }
  ],
  "groups": [],
  "scene_order": [
    {
      "name": "Scene"
    }
  ],
  "current_scene": "Scene",
  "current_program_scene": "Scene",
  "canvases": [],
  "current_transition": "Fade",
  "transition_duration": 300,
  "transitions": [],
  "quick_transitions": [
    {
      "name": "Cut",
      "duration": 300,
      "hotkeys": [],
      "id": 1,
      "fade_to_black": false
    },
    {
      "name": "Fade",
      "duration": 300,
      "hotkeys": [],
      "id": 2,
      "fade_to_black": false
    },
    {
      "name": "Fade",
      "duration": 300,
      "hotkeys": [],
      "id": 3,
      "fade_to_black": true
    }
  ],
  "saved_projectors": [],
  "preview_locked": false,
  "scaling_enabled": false,
  "scaling_level": -18,
  "scaling_off_x": 0.0,
  "scaling_off_y": 0.0,
  "modules": {},
  "resolution": {
    "x": 1366,
    "y": 768
  },
  "version": 2
}

